treeo/__init__.py
treeo/api.py
treeo/mixins.py
treeo/tree.py
treeo/types.py
treeo/utils.py
treeo-0.2.2.dist-info/LICENSE
treeo-0.2.2.dist-info/WHEEL
treeo-0.2.2.dist-info/METADATA
treeo-0.2.2.dist-info/RECORD
