Metadata-Version: 2.1
Name: treeo
Version: 0.2.2
Summary: 
Home-page: https://cgarciae.github.io/treeo
License: MIT
Author: Cristian Garcia
Author-email: cgarcia.e88@gmail.com
Requires-Python: >=3.8,<4.0
Classifier: License :: OSI Approved :: MIT License
Classifier: Programming Language :: Python :: 3
Classifier: Programming Language :: Python :: 3.8
Classifier: Programming Language :: Python :: 3.9
Classifier: Programming Language :: Python :: 3.10
Requires-Dist: typing-extensions (>=3.7.0)
Project-URL: Repository, https://github.com/cgarciae/treeo
